promptcraft/__init__.py
promptcraft/character.py
promptcraft/parrot.py
promptcraft/sentence.py
promptcraft/styleformer.py
promptcraft/word.py
promptcraft-0.4.8.dist-info/LICENSE
promptcraft-0.4.8.dist-info/METADATA
promptcraft-0.4.8.dist-info/WHEEL
promptcraft-0.4.8.dist-info/top_level.txt
promptcraft-0.4.8.dist-info/RECORD
