Metadata-Version: 2.1
Name: promptcraft
Version: 0.4.8
Summary: PromptCraft: A Prompt Perturbation Toolkit for Prompt Robustness Analysis
Home-page: https://github.com/SuperBruceJia/promptcraft
Author: Shuyue Jia
Author-email: shuyuej@ieee.org
License: MIT
Keywords: prompt perturbation,prompt,prompt toolkit,natural language prompt,large language models,llm,llms,prompt engineering,prompt generator,prompt optimization,prompt,prompt robustness,llm robustness,llms adversarial attack,character editing,word manipulation,sentence paraphrasing
Classifier: Development Status :: 4 - Beta
Classifier: Intended Audience :: Science/Research
Classifier: Topic :: Scientific/Engineering :: Artificial Intelligence
Classifier: License :: OSI Approved :: MIT License
Classifier: Programming Language :: Python :: 3.9
License-File: LICENSE
Requires-Dist: torch
Requires-Dist: bitsandbytes
Requires-Dist: transformers
Requires-Dist: pandas
Requires-Dist: Levenshtein
Requires-Dist: scipy
Requires-Dist: sklearn-pandas
Requires-Dist: scikit-learn
Requires-Dist: sentence-transformers
Requires-Dist: googletrans (==3.1.0a0)
Requires-Dist: nltk
Requires-Dist: sacremoses
Requires-Dist: sentencepiece
Requires-Dist: protobuf
